eveimageserver/__init__.py
eveimageserver/main.py
tests/__init__.py
tests/test_main.py
eveimageserver-0.1.2.dist-info/top_level.txt
eveimageserver-0.1.2.dist-info/pbr.json
eveimageserver-0.1.2.dist-info/METADATA
eveimageserver-0.1.2.dist-info/DESCRIPTION.rst
eveimageserver-0.1.2.dist-info/metadata.json
eveimageserver-0.1.2.dist-info/WHEEL
eveimageserver-0.1.2.dist-info/RECORD
