Metadata-Version: 2.0
Name: eveimageserver
Version: 0.1.2
Summary: A collection of utility metods for interacting with the EVE Online image server.
Home-page: https://github.com/Regner/eveimageserver
Author: Regner Blok-Andernse
Author-email: regnerba@gmail.com
License: MIT
Keywords: eve image server
Platform: UNKNOWN
Classifier: Development Status :: 3 - Alpha
Classifier: Topic :: Utilities
Classifier: License :: OSI Approved :: MIT License
